TestModelKsx/__init__.py
TestModelKsx-0.1.4.dist-info/LICENSE.txt
TestModelKsx-0.1.4.dist-info/METADATA
TestModelKsx-0.1.4.dist-info/WHEEL
TestModelKsx-0.1.4.dist-info/top_level.txt
TestModelKsx-0.1.4.dist-info/RECORD
